neuralsage/__init__.py
neuralsage/neuralsage.py
neuralsage/tflite_analyser.py
neuralsage-0.0.1.dev1.dist-info/LICENSE
neuralsage-0.0.1.dev1.dist-info/METADATA
neuralsage-0.0.1.dev1.dist-info/WHEEL
neuralsage-0.0.1.dev1.dist-info/top_level.txt
neuralsage-0.0.1.dev1.dist-info/RECORD
