Metadata-Version: 2.1
Name: neuralsage
Version: 0.0.1.dev1
Summary: A tool to analyse deep learning models
Author-email: Thomas Paul <nivintpaul@gmail.com>
Project-URL: Homepage, https://github.com/mrtpk/neuralsage
Project-URL: Bug Tracker, https://github.com/mrtpk/neuralsage/issues
Classifier: Programming Language :: Python :: 3
Classifier: License :: OSI Approved :: MIT License
Classifier: Operating System :: OS Independent
Requires-Python: >=3.7
License-File: LICENSE
